.gitignore
.travis.yml
MANIFEST.in
README.rst
bootstrap.py
setup.py
travis.cfg
docs/HISTORY.txt
docs/INSTALL.txt
docs/LICENSE.GPL
docs/LICENSE.txt
src/collective/__init__.py
src/collective.geo.settings.egg-info/PKG-INFO
src/collective.geo.settings.egg-info/SOURCES.txt
src/collective.geo.settings.egg-info/dependency_links.txt
src/collective.geo.settings.egg-info/entry_points.txt
src/collective.geo.settings.egg-info/namespace_packages.txt
src/collective.geo.settings.egg-info/not-zip-safe
src/collective.geo.settings.egg-info/requires.txt
src/collective.geo.settings.egg-info/top_level.txt
src/collective/geo/__init__.py
src/collective/geo/settings/README.txt
src/collective/geo/settings/__init__.py
src/collective/geo/settings/config.py
src/collective/geo/settings/configure.zcml
src/collective/geo/settings/events.py
src/collective/geo/settings/field.py
src/collective/geo/settings/interfaces.py
src/collective/geo/settings/profiles.zcml
src/collective/geo/settings/schema.py
src/collective/geo/settings/setuphandlers.py
src/collective/geo/settings/testing.py
src/collective/geo/settings/utils.py
src/collective/geo/settings/vocabularies.py
src/collective/geo/settings/locales/collective.geo.settings.pot
src/collective/geo/settings/locales/rebuild.sh
src/collective/geo/settings/locales/da/LC_MESSAGES/collective.geo.settings.po
src/collective/geo/settings/locales/de/LC_MESSAGES/collective.geo.settings.po
src/collective/geo/settings/locales/es/LC_MESSAGES/collective.geo.settings.po
src/collective/geo/settings/locales/fr/LC_MESSAGES/collective.geo.settings.po
src/collective/geo/settings/locales/it/LC_MESSAGES/collective.geo.settings.po
src/collective/geo/settings/locales/nl/LC_MESSAGES/collective.geo.settings.po
src/collective/geo/settings/locales/pt_BR/LC_MESSAGES/collective.geo.settings.po
src/collective/geo/settings/locales/zh_CN/LC_MESSAGES/collective.geo.settings.po
src/collective/geo/settings/locales/zh_TW/LC_MESSAGES/collective.geo.settings.po
src/collective/geo/settings/profiles/default/metadata.xml
src/collective/geo/settings/profiles/default/registry.xml
src/collective/geo/settings/profiles/uninstall/registry.xml
src/collective/geo/settings/tests/__init__.py
src/collective/geo/settings/tests/test_doctests.py
src/collective/geo/settings/tests/test_setup.py
src/collective/geo/settings/upgrades/__init__.py
src/collective/geo/settings/upgrades/configure.zcml
