Metadata-Version: 1.1
Name: collective.geo.settings
Version: 4.0
Summary: collective.geo settings
Home-page: https://svn.plone.org/svn/collective/collective.geo.settings
Author: Giorgio Borelli
Author-email: giorgio@giorgioborelli.it
License: GPL
Keywords: Zope Plone GIS KML Google Maps Bing OpenLayers
Platform: UNKNOWN
Classifier: Framework :: Plone
Classifier: Topic :: Internet
Classifier: Topic :: Scientific/Engineering :: GIS
Classifier: Programming Language :: Python
